{"original_position": 8, "diff_hunk": "@@ -5,15 +5,20 @@\n   \"main\": \"index.js\",\n   \"author\": \"Mike Cooper <mcooper@mozilla.com>\",\n   \"repository\": \"https://github.com/mozilla/normandy-addon\",\n+  \"scripts\": {},\n+  \"license\": \"MPL-2.0\",\n   \"scripts\": {\n+    \"watch-vendor\": \"webpack --config ./webpack.config.js --watch\",\n+    \"build-bendor\": \"webpack --config ./webpack.config.js\",", "body_text": "typo: bendor", "pull_request_url": "https://api.github.com/repos/mozilla/normandy/pulls/871", "url": "https://api.github.com/repos/mozilla/normandy/pulls/comments/126487346", "created_at": "2017-07-10T17:34:13Z", "author_association": "MEMBER", "body": "typo: bendor", "updated_at": "2017-07-11T17:58:09Z", "html_url": "https://github.com/mozilla/normandy/pull/871#discussion_r126487346", "pull_request_review_id": 48976277, "_links": {"self": {"href": "https://api.github.com/repos/mozilla/normandy/pulls/comments/126487346"}, "html": {"href": "https://github.com/mozilla/normandy/pull/871#discussion_r126487346"}, "pull_request": {"href": "https://api.github.com/repos/mozilla/normandy/pulls/871"}}, "commit_id": "1a7b6d5f928d37c2b9b48f62717c1d62c8c2a150", "user": {"following_url": "https://api.github.com/users/mythmon/following{/other_user}", "events_url": "https://api.github.com/users/mythmon/events{/privacy}", "organizations_url": "https://api.github.com/users/mythmon/orgs", "url": "https://api.github.com/users/mythmon", "gists_url": "https://api.github.com/users/mythmon/gists{/gist_id}", "html_url": "https://github.com/mythmon", "subscriptions_url": "https://api.github.com/users/mythmon/subscriptions", "avatar_url": "https://avatars3.githubusercontent.com/u/305049?v=4", "repos_url": "https://api.github.com/users/mythmon/repos", "received_events_url": "https://api.github.com/users/mythmon/received_events", "gravatar_id": "", "starred_url": "https://api.github.com/users/mythmon/starred{/owner}{/repo}", "site_admin": false, "login": "mythmon", "type": "User", "id": 305049, "followers_url": "https://api.github.com/users/mythmon/followers"}, "position": null, "path": "recipe-client-addon/package.json", "body_html": "<p>typo: bendor</p>", "original_commit_id": "eeded0bdc56a641144e672faf598fe4aa7138c19", "id": 126487346}