{"original_position": 22, "diff_hunk": "@@ -35,13 +35,6 @@ export default function apiFetch(url, options = {}) {\n     delete settings.data;\n   }\n \n-  return fetch(`${API_ROOT}${url}${queryString}`, settings)\n-    .then(response => Promise.all([response.ok, response.json()]))\n-    .catch(error => [false, { message: error.message }])\n-    .then(([ok, data]) => {\n-      if (!ok) {\n-        throw data;\n-      }\n-      return data;\n-    });\n+  const response = await fetch(`${API_ROOT}${url}${queryString}`, settings);\n+  return response.json();", "body_text": "Technically, the await fetch(...) business should be wrapped in a try/catch block to handle errors.", "pull_request_url": "https://api.github.com/repos/mozilla/normandy/pulls/704", "url": "https://api.github.com/repos/mozilla/normandy/pulls/comments/113539497", "created_at": "2017-04-26T19:18:04Z", "author_association": "CONTRIBUTOR", "body": "Technically, the `await fetch(...)` business should be wrapped in a `try/catch` block to handle errors.", "updated_at": "2017-05-03T03:20:26Z", "html_url": "https://github.com/mozilla/normandy/pull/704#discussion_r113539497", "pull_request_review_id": 34937231, "_links": {"self": {"href": "https://api.github.com/repos/mozilla/normandy/pulls/comments/113539497"}, "html": {"href": "https://github.com/mozilla/normandy/pull/704#discussion_r113539497"}, "pull_request": {"href": "https://api.github.com/repos/mozilla/normandy/pulls/704"}}, "commit_id": "f39acceb032bc336aad8cbb3edce72472c143c7e", "user": {"following_url": "https://api.github.com/users/andymikulski/following{/other_user}", "events_url": "https://api.github.com/users/andymikulski/events{/privacy}", "organizations_url": "https://api.github.com/users/andymikulski/orgs", "url": "https://api.github.com/users/andymikulski", "gists_url": "https://api.github.com/users/andymikulski/gists{/gist_id}", "html_url": "https://github.com/andymikulski", "subscriptions_url": "https://api.github.com/users/andymikulski/subscriptions", "avatar_url": "https://avatars1.githubusercontent.com/u/2767162?v=4", "repos_url": "https://api.github.com/users/andymikulski/repos", "received_events_url": "https://api.github.com/users/andymikulski/received_events", "gravatar_id": "", "starred_url": "https://api.github.com/users/andymikulski/starred{/owner}{/repo}", "site_admin": false, "login": "andymikulski", "type": "User", "id": 2767162, "followers_url": "https://api.github.com/users/andymikulski/followers"}, "position": null, "path": "recipe-server/client/control/utils/apiFetch.js", "body_html": "<p>Technically, the <code>await fetch(...)</code> business should be wrapped in a <code>try/catch</code> block to handle errors.</p>", "original_commit_id": "f767487a832d55560b58fd17d95848e0a0788acc", "id": 113539497}