{"original_position": 25, "diff_hunk": "@@ -49,8 +49,29 @@ this.NormandyApi = {\n     return this.apiCall(\"post\", endpoint, data);\n   },\n \n+  apiIndex() {\n+    if (!indexPromise) {\n+      indexPromise = this.get(prefs.getCharPref(\"api_url\")).then(res => res.json);\n+    }\n+    return indexPromise;\n+  },\n+\n+  makeApiUrl(endpoint) {", "body_text": "To be clear, nothing to do here. I'm just sad at JS.", "in_reply_to_id": 101075504, "pull_request_url": "https://api.github.com/repos/mozilla/normandy/pulls/510", "url": "https://api.github.com/repos/mozilla/normandy/pulls/comments/101099958", "created_at": "2017-02-14T17:59:37Z", "author_association": "MEMBER", "body": "To be clear, nothing to do here. I'm just sad at JS.", "updated_at": "2017-02-23T22:37:10Z", "html_url": "https://github.com/mozilla/normandy/pull/510#discussion_r101099958", "pull_request_review_id": 21819902, "_links": {"self": {"href": "https://api.github.com/repos/mozilla/normandy/pulls/comments/101099958"}, "html": {"href": "https://github.com/mozilla/normandy/pull/510#discussion_r101099958"}, "pull_request": {"href": "https://api.github.com/repos/mozilla/normandy/pulls/510"}}, "commit_id": "e83c63174a7ed48da636f574c05d9cbeb11abe04", "user": {"following_url": "https://api.github.com/users/Osmose/following{/other_user}", "events_url": "https://api.github.com/users/Osmose/events{/privacy}", "organizations_url": "https://api.github.com/users/Osmose/orgs", "url": "https://api.github.com/users/Osmose", "gists_url": "https://api.github.com/users/Osmose/gists{/gist_id}", "html_url": "https://github.com/Osmose", "subscriptions_url": "https://api.github.com/users/Osmose/subscriptions", "avatar_url": "https://avatars1.githubusercontent.com/u/193106?v=4", "repos_url": "https://api.github.com/users/Osmose/repos", "received_events_url": "https://api.github.com/users/Osmose/received_events", "gravatar_id": "", "starred_url": "https://api.github.com/users/Osmose/starred{/owner}{/repo}", "site_admin": false, "login": "Osmose", "type": "User", "id": 193106, "followers_url": "https://api.github.com/users/Osmose/followers"}, "position": null, "path": "recipe-client-addon/lib/NormandyApi.jsm", "body_html": "<p>To be clear, nothing to do here. I'm just sad at JS.</p>", "original_commit_id": "b3da82e51da205d0deea69eaa7024170eaba2e51", "id": 101099958}