{"original_position": 22, "diff_hunk": "@@ -0,0 +1,28 @@\n+#!/usr/bin/env bash\n+\n+set -eu\n+\n+BASE_DIR=\"$(dirname \"$(cd \"$(dirname \"${BASH_SOURCE[0]}\")\" && pwd)\")\"\n+TMP_DIR=$(mktemp -d)\n+DEST=\"${TMP_DIR}/shield-recipe-client\"\n+\n+mkdir -p $DEST\n+\n+# deletes the temp directory\n+function cleanup {\n+  rm -rf \"$TMP_DIR\"\n+}\n+trap cleanup EXIT\n+\n+while read -r LINE || [[ -n \"${LINE}\" ]]; do\n+  mkdir -p \"$(dirname \"${DEST}/${LINE}\")\"\n+  cp -r \"${BASE_DIR}/${LINE}\" \"$(dirname \"${DEST}/${LINE}\")\"\n+done < \"${BASE_DIR}/build-includes.txt\"\n+\n+rm \"${DEST}/install.rdf.in\"", "body_text": "This is a part of the Firefox build process. We don't need it for the XPI build process.", "in_reply_to_id": 101848191, "pull_request_url": "https://api.github.com/repos/mozilla/normandy/pulls/514", "url": "https://api.github.com/repos/mozilla/normandy/pulls/comments/102567343", "created_at": "2017-02-22T20:43:37Z", "author_association": "MEMBER", "body": "This is a part of the Firefox build process. We don't need it for the XPI build process.", "updated_at": "2017-02-22T22:33:32Z", "html_url": "https://github.com/mozilla/normandy/pull/514#discussion_r102567343", "pull_request_review_id": 23327347, "_links": {"self": {"href": "https://api.github.com/repos/mozilla/normandy/pulls/comments/102567343"}, "html": {"href": "https://github.com/mozilla/normandy/pull/514#discussion_r102567343"}, "pull_request": {"href": "https://api.github.com/repos/mozilla/normandy/pulls/514"}}, "commit_id": "70c8f16f1f6dae1920dc0c69ba497c1a70db72f4", "user": {"following_url": "https://api.github.com/users/mythmon/following{/other_user}", "events_url": "https://api.github.com/users/mythmon/events{/privacy}", "organizations_url": "https://api.github.com/users/mythmon/orgs", "url": "https://api.github.com/users/mythmon", "gists_url": "https://api.github.com/users/mythmon/gists{/gist_id}", "html_url": "https://github.com/mythmon", "subscriptions_url": "https://api.github.com/users/mythmon/subscriptions", "avatar_url": "https://avatars3.githubusercontent.com/u/305049?v=4", "repos_url": "https://api.github.com/users/mythmon/repos", "received_events_url": "https://api.github.com/users/mythmon/received_events", "gravatar_id": "", "starred_url": "https://api.github.com/users/mythmon/starred{/owner}{/repo}", "site_admin": false, "login": "mythmon", "type": "User", "id": 305049, "followers_url": "https://api.github.com/users/mythmon/followers"}, "position": 22, "path": "recipe-client-addon/bin/make-xpi.sh", "body_html": "<p>This is a part of the Firefox build process. We don't need it for the XPI build process.</p>", "original_commit_id": "9aebecda4af23261221c85a290520b002e45a649", "id": 102567343}