{"original_position": 25, "diff_hunk": "@@ -0,0 +1,66 @@\n+import React from 'react';\n+import PropTypes from 'prop-types';\n+import autobind from 'autobind-decorator';\n+import { connect } from 'react-redux';\n+import { Breadcrumb } from 'antd';\n+import { Link } from 'redux-little-router';\n+\n+@autobind\n+export class NavigationCrumbs extends React.Component {\n+  static propTypes = {\n+    router: PropTypes.object.isRequired,\n+  };\n+  state = { breadcrumbs: [] };\n+\n+  componentDidMount() {\n+    this.updateBreadcrumbs(this.props.router);\n+  }\n+\n+  componentWillReceiveProps({ router }) {\n+    this.updateBreadcrumbs(router || this.props.router);\n+  }\n+\n+  // Given a router, gathers the steps leading down to the current route, to be\n+  // displayed as breadcrumbs.\n+  updateBreadcrumbs(router) {", "body_text": "maybe name this gatherBreadcrumbs and then you don't need the comment.", "pull_request_url": "https://api.github.com/repos/mozilla/normandy/pulls/844", "url": "https://api.github.com/repos/mozilla/normandy/pulls/comments/124645768", "created_at": "2017-06-28T20:19:36Z", "author_association": "MEMBER", "body": "maybe name this `gatherBreadcrumbs` and then you don't need the comment.", "updated_at": "2017-06-28T22:24:44Z", "html_url": "https://github.com/mozilla/normandy/pull/844#discussion_r124645768", "pull_request_review_id": 46955718, "_links": {"self": {"href": "https://api.github.com/repos/mozilla/normandy/pulls/comments/124645768"}, "html": {"href": "https://github.com/mozilla/normandy/pull/844#discussion_r124645768"}, "pull_request": {"href": "https://api.github.com/repos/mozilla/normandy/pulls/844"}}, "commit_id": "5ee41fa22f76132829b1c44c4d30ac14683b8fb8", "user": {"following_url": "https://api.github.com/users/rehandalal/following{/other_user}", "events_url": "https://api.github.com/users/rehandalal/events{/privacy}", "organizations_url": "https://api.github.com/users/rehandalal/orgs", "url": "https://api.github.com/users/rehandalal", "gists_url": "https://api.github.com/users/rehandalal/gists{/gist_id}", "html_url": "https://github.com/rehandalal", "subscriptions_url": "https://api.github.com/users/rehandalal/subscriptions", "avatar_url": "https://avatars2.githubusercontent.com/u/987136?v=4", "repos_url": "https://api.github.com/users/rehandalal/repos", "received_events_url": "https://api.github.com/users/rehandalal/received_events", "gravatar_id": "", "starred_url": "https://api.github.com/users/rehandalal/starred{/owner}{/repo}", "site_admin": false, "login": "rehandalal", "type": "User", "id": 987136, "followers_url": "https://api.github.com/users/rehandalal/followers"}, "position": null, "path": "recipe-server/client/control_new/components/common/NavigationCrumbs.js", "body_html": "<p>maybe name this <code>gatherBreadcrumbs</code> and then you don't need the comment.</p>", "original_commit_id": "d1f925944b37466d23d91e9c8ef53d9a6e6396f5", "id": 124645768}